setup.py
eveapimongo/__init__.py
eveapimongo/apiWrapper.py
eveapimongo/mongoFactory.py
eveapimongo/mongoProvider.py
eveapimongo.egg-info/PKG-INFO
eveapimongo.egg-info/SOURCES.txt
eveapimongo.egg-info/dependency_links.txt
eveapimongo.egg-info/not-zip-safe
eveapimongo.egg-info/requires.txt
eveapimongo.egg-info/top_level.txt