Metadata-Version: 1.0
Name: eveapimongo
Version: 0.1
Summary: EvE-API and MongoDB Wrappers
Home-page: UNKNOWN
Author: Michael Bahr
Author-email: UNKNOWN
License: MIT
Platform: UNKNOWN
